{
  "timestamp": "2026-02-11 12:58:07",
  "defaults": {
    "max_voltage": 3.3,
    "dipole_strength": 2.88
  },
  "kbdot": 400000.0,
  "best": {
    "kp": 0.002486363,
    "ki": 1e-05,
    "kd": 0.105474673,
    "agg": 143.3763559125
  },
  "stage1_top6": [
    {
      "kp": 0.003226533,
      "ki": 6e-05,
      "kd": 0.155603999,
      "score": 31.903462422222223
    },
    {
      "kp": 0.003326551,
      "ki": 1e-05,
      "kd": 0.152292994,
      "score": 31.90397262222222
    },
    {
      "kp": 0.002069315,
      "ki": 0.0,
      "kd": 0.103765987,
      "score": 31.963204261111112
    },
    {
      "kp": 0.002460756,
      "ki": 1e-05,
      "kd": 0.148551671,
      "score": 32.017119422222216
    },
    {
      "kp": 0.002225432,
      "ki": 3e-05,
      "kd": 0.152860391,
      "score": 32.14229276111111
    },
    {
      "kp": 0.002486363,
      "ki": 1e-05,
      "kd": 0.105474673,
      "score": 32.25096231111111
    }
  ]
}